pandasai_oracle/__init__.py
pandasai_oracle-0.1.4.dist-info/LICENSE
pandasai_oracle-0.1.4.dist-info/METADATA
pandasai_oracle-0.1.4.dist-info/WHEEL
pandasai_oracle-0.1.4.dist-info/RECORD
